README.md
setup.cfg
setup.py
minus80/Accession.py
minus80/CloudData.py
minus80/Cohort.py
minus80/ColumnDB.py
minus80/Config.py
minus80/Exceptions.py
minus80/FireBaseCloudData.py
minus80/Freezable.py
minus80/GCPCloudData.py
minus80/Project.py
minus80/RawFile.py
minus80/RelationalDB.py
minus80/Tools.py
minus80/__init__.py
minus80.egg-info/PKG-INFO
minus80.egg-info/SOURCES.txt
minus80.egg-info/dependency_links.txt
minus80.egg-info/entry_points.txt
minus80.egg-info/requires.txt
minus80.egg-info/top_level.txt
minus80/cli/__init__.py
minus80/cli/minus80.py