Metadata-Version: 2.1
Name: minus80
Version: 1.0.0
Summary: A library for freezing, unfreezing and storing biological data.
Home-page: http://linkage.io
Author: Rob Schaefer
Author-email: rob@linkage.io
License: Copyright Linkage Analytics 2016-2018. Available under the MIT License
Project-URL: Documentation, https://minus80.readthedocs.io/en/latest/
Project-URL: Source, https://github.com/LinkageIO/Minus80
Project-URL: Tracker, https://github.com/LinkageIO/Minus80/issues
Keywords: data storage biology freeze
Platform: UNKNOWN
Classifier: Development Status :: 4 - Beta
Classifier: Intended Audience :: Developers
Classifier: Topic :: Software Development :: Build Tools
Classifier: License :: OSI Approved :: MIT License
Classifier: Programming Language :: Python :: 3
Classifier: Programming Language :: Python :: 3.6
Provides-Extra: docs
